{
    "thumbnail_size": 200,
    "preview_resolution": "480x854",
    "volume": 60,
    "vertical_mode": true,
    "play_on_hover": false,
    "columns": 6,
    "last_folder": "C:/Users/norma/Desktop/Fitness Vid\u00e9os",
    "target_folder": "C:/Users/norma/Videos/DaVinci Resolve Projects/Cineblast/2026-06-29 Toxic Avenger (1984)",
    "copy_shortcut": "Ctrl+C",
    "show_quick_copy_buttons": false,
    "last_active_folder": "C:/Users/norma/Desktop/Fitness Vid\u00e9os",
    "last_include_subdirs": true,
    "last_root_files_only": false,
    "tooltip_font_size": 120,
    "view_mode": "thumbnails",
    "lazy_loading": true,
    "backup_destinations": [],
    "explorer_mode": "tags",
    "last_tag_filter": [
        [
            "system",
            "untagged"
        ]
    ],
    "last_valence_filter": null,
    "last_target_browse_folder": "C:/Users/norma/Videos/DaVinci Resolve Projects/Cineblast/2026-06-29 Toxic Avenger (1984)",
    "folder_fr": "C:/Users/norma/Desktop/Fitness Vid\u00e9os",
    "folder_en": "C:/Users/norma/Desktop/Fitness Vid\u00e9os",
    "active_source": "fr",
    "window_width": 2092,
    "window_height": 1345
}